concrete_backend-0.0.10-py3.9-nspkg.pth
concrete/backend/__init__.py
concrete/backend/file.py
concrete_backend-0.0.10.dist-info/LICENSE
concrete_backend-0.0.10.dist-info/METADATA
concrete_backend-0.0.10.dist-info/WHEEL
concrete_backend-0.0.10.dist-info/namespace_packages.txt
concrete_backend-0.0.10.dist-info/top_level.txt
concrete_backend-0.0.10.dist-info/RECORD
